setup.py
BadLinksPlugin.egg-info/PKG-INFO
BadLinksPlugin.egg-info/SOURCES.txt
BadLinksPlugin.egg-info/dependency_links.txt
BadLinksPlugin.egg-info/entry_points.txt
BadLinksPlugin.egg-info/not-zip-safe
BadLinksPlugin.egg-info/top_level.txt
badlinks/__init__.py
badlinks/api.py