Metadata-Version: 1.0
Name: BadLinksPlugin
Version: 0.1.1
Summary: Log bad local links found in wiki content.
Home-page: http://mitar.tnode.com/
Author: Mitar
Author-email: mitar.trac@tnode.com
License: AGPLv3
Keywords: trac plugin
Platform: UNKNOWN
